README.rst
flatdoc.py
setup.py
flatdoc.egg-info/PKG-INFO
flatdoc.egg-info/SOURCES.txt
flatdoc.egg-info/dependency_links.txt
flatdoc.egg-info/entry_points.txt
flatdoc.egg-info/requires.txt
flatdoc.egg-info/top_level.txt