Metadata-Version: 1.1
Name: flatdoc
Version: 0.1.0
Summary: Docstring flat documentation generator
Home-page: https://github.com/miguelgrinberg/flatdoc
Author: Miguel Grinberg
Author-email: miguelgrinberg50@gmail.com
License: MIT
Platform: UNKNOWN
Classifier: Intended Audience :: Developers
Classifier: License :: OSI Approved :: MIT License
Classifier: Programming Language :: Python
Classifier: Programming Language :: Python :: 2
Classifier: Programming Language :: Python :: 3
Classifier: Topic :: Software Development :: Libraries
Classifier: Topic :: Software Development :: Libraries :: Python Modules
